trame/__init__.py
trame/modules/__init__.py
trame/modules/trame_pvui.py
trame/widgets/__init__.py
trame/widgets/pvui.py
trame_pvui/__init__.py
trame_pvui/module/__init__.py
trame_pvui/module/serve/demo.html
trame_pvui/module/serve/pvui.common.js
trame_pvui/module/serve/pvui.common.js.map
trame_pvui/module/serve/pvui.css
trame_pvui/module/serve/pvui.umd.js
trame_pvui/module/serve/pvui.umd.js.map
trame_pvui/module/serve/pvui.umd.min.js
trame_pvui/module/serve/pvui.umd.min.js.map
trame_pvui/widgets/__init__.py
trame_pvui/widgets/colormapper.py
trame_pvui/widgets/filebrowser.py
trame_pvui/widgets/infopanel.py
trame_pvui/widgets/serverbrowser.py
trame_pvui/widgets/widget.py
trame_pvui-0.1.1.dist-info/LICENSE
trame_pvui-0.1.1.dist-info/METADATA
trame_pvui-0.1.1.dist-info/WHEEL
trame_pvui-0.1.1.dist-info/top_level.txt
trame_pvui-0.1.1.dist-info/RECORD
